django_silverlance-0.2.1318.dist-info/METADATA
django_silverlance-0.2.1318.dist-info/RECORD
django_silverlance-0.2.1318.dist-info/WHEEL
django_silverlance-0.2.1318.dist-info/top_level.txt
silverlance/__init__.py
silverlance/apps.py
silverlance/models.py
